meilisearch_mcp/__init__.py
meilisearch_mcp/__main__.py
meilisearch_mcp/client.py
meilisearch_mcp/documents.py
meilisearch_mcp/indexes.py
meilisearch_mcp/keys.py
meilisearch_mcp/logging.py
meilisearch_mcp/monitoring.py
meilisearch_mcp/server.py
meilisearch_mcp/settings.py
meilisearch_mcp/tasks.py
meilisearch_mcp_upd-0.5.3.dist-info/LICENSE
meilisearch_mcp_upd-0.5.3.dist-info/METADATA
meilisearch_mcp_upd-0.5.3.dist-info/WHEEL
meilisearch_mcp_upd-0.5.3.dist-info/entry_points.txt
meilisearch_mcp_upd-0.5.3.dist-info/top_level.txt
meilisearch_mcp_upd-0.5.3.dist-info/RECORD
