Metadata-Version: 2.2
Name: meilisearch-mcp-upd
Version: 0.5.3
Summary: MCP server for Meilisearch
Requires-Python: >=3.10
License-File: LICENSE
Requires-Dist: meilisearch>=0.33.0
Requires-Dist: mcp>=0.1.0
Requires-Dist: httpx>=0.24.0
Requires-Dist: pydantic>=2.0.0
